{
  "date": "2026-06-25",
  "posts": [
    {
      "time": "13:10:05",
      "specialty": "معلومة تاريخية قصيرة",
      "content": "أُجريت أول عملية نقل قلب في عام 1967 على يد الجراح كريستيان برنارد في جنوب أفريقيا. وكان المريض الذي خضع للعمليّة هو لويس واشكانسكي، ولبث على قيد الحياة لمدة 18 يوماً بعد العمليّة.",
      "status": "success"
    },
    {
      "time": "22:08:23",
      "specialty": "معلومة مفيدة للحياة",
      "content": "يُفضل شرب كوب من الماء الدافئ بعد الاستيقاظ لتحفيز الجهاز الهضمي وتحسين الوقاية من الأمراض. يُساعد شرب الماء الدافئ أيضًا على تنشيط الدورة الدموية وزيادة الطاقة.",
      "status": "success"
    }
  ]
}